django_dynamic_maintenance_mode-0.1.0.dist-info/licenses/LICENSE
dynamic_maintenance/__init__.py
dynamic_maintenance/admin.py
dynamic_maintenance/apps.py
dynamic_maintenance/middleware.py
dynamic_maintenance/models.py
dynamic_maintenance/migrations/__init__.py
django_dynamic_maintenance_mode-0.1.0.dist-info/METADATA
django_dynamic_maintenance_mode-0.1.0.dist-info/WHEEL
django_dynamic_maintenance_mode-0.1.0.dist-info/top_level.txt
django_dynamic_maintenance_mode-0.1.0.dist-info/RECORD
