Metadata-Version: 2.4
Name: django-dynamic-maintenance-mode
Version: 0.1.0
Summary: Django middleware to enable maintenance mode dynamically using a database flag.
Home-page: https://github.com/pranav-dixit/django-dynamic-maintenance-mode
Author: Pranav Dixit
Author-email: pranavdixit20@gmail.com
License: MIT
Classifier: Environment :: Web Environment
Classifier: Framework :: Django
Classifier: Framework :: Django :: 4.1
Classifier: Intended Audience :: Developers
Classifier: License :: OSI Approved :: MIT License
Classifier: Programming Language :: Python :: 3
Requires-Python: >=3.7
License-File: LICENSE
Requires-Dist: Django>=3.2
Dynamic: author
Dynamic: author-email
Dynamic: classifier
Dynamic: description
Dynamic: description-content-type
Dynamic: home-page
Dynamic: license
Dynamic: license-file
Dynamic: requires-dist
Dynamic: requires-python
Dynamic: summary
